kore_plugins_flask/__init__.py
kore_plugins_flask/application/__init__.py
kore_plugins_flask/application/factories.py
kore_plugins_flask/plugins/__init__.py
kore_plugins_flask/plugins/application.py
kore_plugins_flask-0.0.4.data/scripts/kore-flask-run
kore_plugins_flask-0.0.4.dist-info/DESCRIPTION.rst
kore_plugins_flask-0.0.4.dist-info/entry_points.txt
kore_plugins_flask-0.0.4.dist-info/METADATA
kore_plugins_flask-0.0.4.dist-info/metadata.json
kore_plugins_flask-0.0.4.dist-info/RECORD
kore_plugins_flask-0.0.4.dist-info/top_level.txt
kore_plugins_flask-0.0.4.dist-info/WHEEL
